{
  "devices": [
    {
      "anchor": "0.025 0.194 -0.16",
      "axis": "0 0 -1",
      "maxPosition": 1.5,
      "minPosition": -1.11,
      "name": "arm_left_1_joint",
      "position": 0,
      "transformID": "n43663",
      "type": "RotationalMotor"
    },
    {
      "anchor": "0.125 0.0195 -0.031",
      "axis": "0 1 0",
      "maxPosition": 1.5,
      "minPosition": -1.11,
      "name": "arm_left_2_joint",
      "position": 0,
      "transformID": "n43696",
      "type": "RotationalMotor"
    },
    {
      "anchor": "0.0895 0 -0.0015",
      "axis": "1 0 0",
      "maxPosition": 3.86,
      "minPosition": -0.72,
      "name": "arm_left_3_joint",
      "position": 0,
      "transformID": "n43710",
      "type": "RotationalMotor"
    },
    {
      "anchor": "-0.02 -0.027 -0.222",
      "axis": "0 1 0",
      "maxPosition": 2.29,
      "minPosition": -0.32,
      "name": "arm_left_4_joint",
      "position": 0,
      "transformID": "n43744",
      "type": "RotationalMotor"
    },
    {
      "anchor": "-0.162 0.02 0.027",
      "axis": "1 0 0",
      "maxPosition": 2.07,
      "minPosition": -2.07,
      "name": "arm_left_5_joint",
      "position": 0,
      "transformID": "n43778",
      "type": "RotationalMotor"
    },
    {
      "anchor": "0 0 0.15",
      "axis": "0 -1 0",
      "maxPosition": 1.39,
      "minPosition": -1.39,
      "name": "arm_left_6_joint",
      "position": 0,
      "transformID": "n43793",
      "type": "RotationalMotor"
    },
    {
      "anchor": "0 0 0",
      "axis": "-1 0 0",
      "maxPosition": 2.07,
      "minPosition": -2.07,
      "name": "arm_left_7_joint",
      "position": 0,
      "transformID": "n43808",
      "type": "RotationalMotor"
    },
    {
      "anchor": "0.025 -0.194 -0.17",
      "axis": "0 0 1",
      "maxPosition": 1.5,
      "minPosition": -1.11,
      "name": "arm_right_1_joint",
      "position": 0,
      "transformID": "n42218",
      "type": "RotationalMotor"
    },
    {
      "anchor": "-0.125 0.0195 -0.031",
      "axis": "0 -1 0",
      "maxPosition": 1.5,
      "minPosition": -1.11,
      "name": "arm_right_2_joint",
      "position": 0,
      "transformID": "n42252",
      "type": "RotationalMotor"
    },
    {
      "anchor": "0.0895 0 -0.0015",
      "axis": "1 0 0",
      "maxPosition": 3.86,
      "minPosition": -0.72,
      "name": "arm_right_3_joint",
      "position": 0,
      "transformID": "n42266",
      "type": "RotationalMotor"
    },
    {
      "anchor": "0.02 0 -0.223",
      "axis": "0 -1 0",
      "maxPosition": 2.29,
      "minPosition": -0.32,
      "name": "arm_right_4_joint",
      "position": 0,
      "transformID": "n42300",
      "type": "RotationalMotor"
    },
    {
      "anchor": "0.163 0.02 0.027",
      "axis": "1 0 0",
      "maxPosition": 2.07,
      "minPosition": -2.07,
      "name": "arm_right_5_joint",
      "position": 0,
      "transformID": "n42334",
      "type": "RotationalMotor"
    },
    {
      "anchor": "0 0 0.15",
      "axis": "0 -1 0",
      "maxPosition": 1.39,
      "minPosition": -1.39,
      "name": "arm_right_6_joint",
      "position": 0,
      "transformID": "n42349",
      "type": "RotationalMotor"
    },
    {
      "anchor": "0 0 0",
      "axis": "-1 0 0",
      "maxPosition": 2.07,
      "minPosition": -2.07,
      "name": "arm_right_7_joint",
      "position": 0,
      "transformID": "n42364",
      "type": "RotationalMotor"
    },
    {
      "anchor": "0.182 0 0",
      "axis": "0 0 1",
      "maxPosition": 1.24,
      "minPosition": -1.24,
      "name": "head_1_joint",
      "position": 0,
      "transformID": "n38036",
      "type": "RotationalMotor"
    },
    {
      "anchor": "0.005 0 0.098",
      "axis": "0 -1 0",
      "maxPosition": 0.79,
      "minPosition": -0.98,
      "name": "head_2_joint",
      "position": 0,
      "transformID": "n38051",
      "type": "RotationalMotor"
    },
    {
      "anchor": "0 0.2022 0",
      "axis": "0 1 0",
      "maxPosition": 0,
      "minPosition": 0,
      "name": "wheel_left_joint",
      "position": 0,
      "transformID": "n11617",
      "type": "RotationalMotor"
    },
    {
      "anchor": "0 -0.2022 0",
      "axis": "0 1 0",
      "maxPosition": 0,
      "minPosition": 0,
      "name": "wheel_right_joint",
      "position": 0,
      "transformID": "n11584",
      "type": "RotationalMotor"
    },
    {
      "anchor": "0 0 0",
      "axis": "-1 0 0",
      "maxPosition": 0.045,
      "minPosition": 0,
      "name": "left_hand_gripper_left_finger_joint",
      "position": 0,
      "transformID": "n48863",
      "type": "LinearMotor"
    },
    {
      "anchor": "0 0 0",
      "axis": "1 0 0",
      "maxPosition": 0.045,
      "minPosition": 0,
      "name": "left_hand_gripper_right_finger_joint",
      "position": 0,
      "transformID": "n48896",
      "type": "LinearMotor"
    },
    {
      "anchor": "0 0 0",
      "axis": "-1 0 0",
      "maxPosition": 0.045,
      "minPosition": 0,
      "name": "right_hand_gripper_left_finger_joint",
      "position": 0,
      "transformID": "n46948",
      "type": "LinearMotor"
    },
    {
      "anchor": "0 0 0",
      "axis": "1 0 0",
      "maxPosition": 0.045,
      "minPosition": 0,
      "name": "right_hand_gripper_right_finger_joint",
      "position": 0,
      "transformID": "n46981",
      "type": "LinearMotor"
    },
    {
      "anchor": "0 0 0",
      "axis": "0 0 1",
      "maxPosition": 0.35,
      "minPosition": 0,
      "name": "torso_lift_joint",
      "position": 0,
      "transformID": "n35122",
      "type": "LinearMotor"
    },
    {
      "name": "accelerometer",
      "transformID": "n1290",
      "type": "Accelerometer"
    },
    {
      "name": "arm_left_1_joint_sensor",
      "transformID": "n43663",
      "type": "PositionSensor"
    },
    {
      "name": "arm_left_2_joint_sensor",
      "transformID": "n43696",
      "type": "PositionSensor"
    },
    {
      "name": "arm_left_3_joint_sensor",
      "transformID": "n43710",
      "type": "PositionSensor"
    },
    {
      "name": "arm_left_4_joint_sensor",
      "transformID": "n43744",
      "type": "PositionSensor"
    },
    {
      "name": "arm_left_5_joint_sensor",
      "transformID": "n43778",
      "type": "PositionSensor"
    },
    {
      "name": "arm_left_6_joint_sensor",
      "transformID": "n43793",
      "type": "PositionSensor"
    },
    {
      "name": "arm_left_7_joint_sensor",
      "transformID": "n43808",
      "type": "PositionSensor"
    },
    {
      "name": "arm_right_1_joint_sensor",
      "transformID": "n42218",
      "type": "PositionSensor"
    },
    {
      "name": "arm_right_2_joint_sensor",
      "transformID": "n42252",
      "type": "PositionSensor"
    },
    {
      "name": "arm_right_3_joint_sensor",
      "transformID": "n42266",
      "type": "PositionSensor"
    },
    {
      "name": "arm_right_4_joint_sensor",
      "transformID": "n42300",
      "type": "PositionSensor"
    },
    {
      "name": "arm_right_5_joint_sensor",
      "transformID": "n42334",
      "type": "PositionSensor"
    },
    {
      "name": "arm_right_6_joint_sensor",
      "transformID": "n42349",
      "type": "PositionSensor"
    },
    {
      "name": "arm_right_7_joint_sensor",
      "transformID": "n42364",
      "type": "PositionSensor"
    },
    {
      "name": "base_cover_link",
      "transformID": "n11517",
      "type": "TouchSensor"
    },
    {
      "name": "base_sonar_01_link",
      "transformID": "n11562",
      "type": "DistanceSensor"
    },
    {
      "name": "base_sonar_02_link",
      "transformID": "n11544",
      "type": "DistanceSensor"
    },
    {
      "name": "base_sonar_03_link",
      "transformID": "n11526",
      "type": "DistanceSensor"
    },
    {
      "name": "gyro",
      "transformID": "n1290",
      "type": "Gyro"
    },
    {
      "name": "head_1_joint_sensor",
      "transformID": "n38036",
      "type": "PositionSensor"
    },
    {
      "name": "head_2_joint_sensor",
      "transformID": "n38051",
      "type": "PositionSensor"
    },
    {
      "name": "Hokuyo URG-04LX-UG01",
      "transformID": "n45092",
      "type": "Lidar"
    },
    {
      "name": "inertial unit",
      "transformID": "n1290",
      "type": "InertialUnit"
    },
    {
      "name": "left_hand_gripper_left_finger_joint_sensor",
      "transformID": "n48863",
      "type": "PositionSensor"
    },
    {
      "name": "left_hand_gripper_right_finger_joint_sensor",
      "transformID": "n48896",
      "type": "PositionSensor"
    },
    {
      "name": "right_hand_gripper_left_finger_joint_sensor",
      "transformID": "n46948",
      "type": "PositionSensor"
    },
    {
      "name": "right_hand_gripper_right_finger_joint_sensor",
      "transformID": "n46981",
      "type": "PositionSensor"
    },
    {
      "name": "torso_lift_joint_sensor",
      "transformID": "n35122",
      "type": "PositionSensor"
    },
    {
      "name": "wheel_left_joint_sensor",
      "transformID": "n11617",
      "type": "PositionSensor"
    },
    {
      "name": "wheel_right_joint_sensor",
      "transformID": "n11584",
      "type": "PositionSensor"
    }
  ],
  "name": "tiagopp",
  "robotID": "n1290"
}
