{
  "robotID": "n12", 
  "name": "koala", 
  "devices": [
    {
      "transformID": "n52", 
      "initialPosition": 4.5282446, 
      "name": "left wheel motor", 
      "maxPosition": 0, 
      "position": 0, 
      "type": "RotationalMotor", 
      "minPosition": 0, 
      "axis": "-1 0 0"
    }, 
    {
      "transformID": "n98", 
      "initialPosition": 3.6118637, 
      "name": "right wheel motor", 
      "maxPosition": 0, 
      "position": 0, 
      "type": "RotationalMotor", 
      "minPosition": 0, 
      "axis": "-1 0 0"
    }, 
    {
      "transformID": "n134", 
      "type": "DistanceSensor", 
      "name": "ds0"
    }, 
    {
      "transformID": "n138", 
      "type": "DistanceSensor", 
      "name": "ds1"
    }, 
    {
      "transformID": "n174", 
      "type": "DistanceSensor", 
      "name": "ds10"
    }, 
    {
      "transformID": "n178", 
      "type": "DistanceSensor", 
      "name": "ds11"
    }, 
    {
      "transformID": "n182", 
      "type": "DistanceSensor", 
      "name": "ds12"
    }, 
    {
      "transformID": "n186", 
      "type": "DistanceSensor", 
      "name": "ds13"
    }, 
    {
      "transformID": "n190", 
      "type": "DistanceSensor", 
      "name": "ds14"
    }, 
    {
      "transformID": "n194", 
      "type": "DistanceSensor", 
      "name": "ds15"
    }, 
    {
      "transformID": "n142", 
      "type": "DistanceSensor", 
      "name": "ds2"
    }, 
    {
      "transformID": "n146", 
      "type": "DistanceSensor", 
      "name": "ds3"
    }, 
    {
      "transformID": "n150", 
      "type": "DistanceSensor", 
      "name": "ds4"
    }, 
    {
      "transformID": "n154", 
      "type": "DistanceSensor", 
      "name": "ds5"
    }, 
    {
      "transformID": "n158", 
      "type": "DistanceSensor", 
      "name": "ds6"
    }, 
    {
      "transformID": "n162", 
      "type": "DistanceSensor", 
      "name": "ds7"
    }, 
    {
      "transformID": "n166", 
      "type": "DistanceSensor", 
      "name": "ds8"
    }, 
    {
      "transformID": "n170", 
      "type": "DistanceSensor", 
      "name": "ds9"
    }, 
    {
      "transformID": "n52", 
      "type": "PositionSensor", 
      "name": "left wheel sensor"
    }, 
    {
      "transformID": "n98", 
      "type": "PositionSensor", 
      "name": "right wheel sensor"
    }
  ]
}
